grok_export_viewer/__init__.py
grok_export_viewer/cli.py
grok_export_viewer/core.py
grok_export_viewer-0.1.3.dist-info/METADATA
grok_export_viewer-0.1.3.dist-info/WHEEL
grok_export_viewer-0.1.3.dist-info/entry_points.txt
grok_export_viewer-0.1.3.dist-info/licenses/LICENSE
grok_export_viewer-0.1.3.dist-info/RECORD
