Metadata-Version: 2.4
Name: grok-export-viewer
Version: 0.1.3
Summary: Convert and browse Grok Chat export JSON as Markdown, HTML, CSV, SQLite, and JSON.
Project-URL: Homepage, https://github.com/beejaksharam/grok-export-viewer
Project-URL: Repository, https://github.com/beejaksharam/grok-export-viewer
Project-URL: Issues, https://github.com/beejaksharam/grok-export-viewer/issues
Project-URL: Changelog, https://github.com/beejaksharam/grok-export-viewer/blob/main/CHANGELOG.md
Author: 12suresa
License: MIT
License-File: LICENSE
Keywords: chat,converter,csv,export,grok,html,json,markdown,sqlite
Classifier: Development Status :: 3 - Alpha
Classifier: Intended Audience :: Developers
Classifier: License :: OSI Approved :: MIT License
Classifier: Programming Language :: Python :: 3
Classifier: Programming Language :: Python :: 3.8
Classifier: Programming Language :: Python :: 3.9
Classifier: Programming Language :: Python :: 3.10
Classifier: Programming Language :: Python :: 3.11
Classifier: Programming Language :: Python :: 3.12
Classifier: Topic :: Text Processing
Classifier: Topic :: Utilities
Requires-Python: >=3.8
Requires-Dist: markdown<4.0,>=3.4.1
Requires-Dist: pygments<3.0,>=2.15.0
Requires-Dist: tqdm<5.0,>=4.66.0
Provides-Extra: test
Requires-Dist: pytest-cov>=4.0; extra == 'test'
Requires-Dist: pytest>=7.0; extra == 'test'
